yflow/__init__.py
yflow/_typing.py
yflow/main.py
yflow/test.ipynb
yflow/utils.py
yflow/config/__init__.py
yflow/config/base_config.py
yflow/config/const.py
yflow/config/cli/__init__.py
yflow/config/cli/args_config.py
yflow/config/extractor/__init__.py
yflow/config/extractor/extractor_config.py
yflow/config/extractor/extractor_config.yaml
yflow/config/pipeline/__init__.py
yflow/config/pipeline/pipeline_config.py
yflow/config/pipeline/connections/__init__.py
yflow/config/pipeline/connections/clickhouse_config.py
yflow/config/pipeline/connections/minio_config.py
yflow/config/pipeline/destinations/__init__.py
yflow/config/pipeline/destinations/destination_config.py
yflow/config/pipeline/joins/__init__.py
yflow/config/pipeline/joins/join_config.py
yflow/config/pipeline/sources/__init__.py
yflow/config/pipeline/sources/minio_config.py
yflow/config/pipeline/sources/source_config.py
yflow/config/pipeline/transforms/__init__.py
yflow/config/pipeline/transforms/base_config.py
yflow/config/pipeline/transforms/cast_rename_config.py
yflow/config/pipeline/transforms/datetime_config.py
yflow/config/pipeline/transforms/filter_config.py
yflow/config/pipeline/transforms/replace_config.py
yflow/config/pipeline/transforms/string_config.py
yflow/config/source/__init__.py
yflow/config/source/minio_config.py
yflow/config/source/source_config.py
yflow/config/source/source_config.yaml
yflow/config/transformer/__init__.py
yflow/config/transformer/config/__init__.py
yflow/config/transformer/config/transformation_config.py
yflow/config/transformer/config/transformation_config.yaml
yflow/config/transformer/function/__init__.py
yflow/config/transformer/function/transformation_function.py
yflow/config/transformer/function/transformation_function.yaml
yflow/core/__init__.py
yflow/core/core.py
yflow/core/test.py
yflow/core/utils.py
yflow/core/extract/__init__.py
yflow/core/extract/clickhouse_extractor.py
yflow/core/extract/csv_extractors.py
yflow/core/extract/extractor.py
yflow-0.1.0.dist-info/METADATA
yflow-0.1.0.dist-info/WHEEL
yflow-0.1.0.dist-info/entry_points.txt
yflow-0.1.0.dist-info/RECORD
