Metadata-Version: 2.4
Name: yflow
Version: 0.1.0
Summary: Ví dụ Hydra CLI
Author-email: Ban <ban@example.com>
Requires-Python: >=3.12.9
